openlist_server/__init__.py
openlist_server/cli.py
openlist_server-0.0.1.dist-info/entry_points.txt
openlist_server-0.0.1.dist-info/WHEEL
openlist_server-0.0.1.dist-info/METADATA
openlist_server-0.0.1.dist-info/RECORD
