Metadata-Version: 2.1
Name: openlist-server
Version: 0.0.1
Summary: OpenList backend server API.
Home-page: https://github.com/gruvw/openlist-server
Author: gruvw
Author-email: gruvw.dev@gmail.com
Requires-Python: >=3.9,<4.0
Classifier: Programming Language :: Python :: 3
Classifier: Programming Language :: Python :: 3.9
Requires-Dist: click (>=8.0.1,<9.0.0)
